reflex_type_animation/__init__.py
reflex_type_animation/type_animation.py
reflex_type_animation-0.0.1.dist-info/METADATA
reflex_type_animation-0.0.1.dist-info/WHEEL
reflex_type_animation-0.0.1.dist-info/top_level.txt
reflex_type_animation-0.0.1.dist-info/RECORD
