Metadata-Version: 2.1
Name: reflex-type-animation
Version: 0.0.1
Summary: Reflex custom component type-animation
Author-email: Elijah Ahianyo <elijahahianyo@gmail.com>
License: Apache-2.0
Project-URL: Homepage, https://github.com/ElijahAhianyo/reflex-type-animation
Keywords: reflex,reflex-custom-components,typing animation
Classifier: Development Status :: 4 - Beta
Requires-Python: >=3.8
Requires-Dist: reflex>=0.4.2
Provides-Extra: dev
Requires-Dist: build; extra == "dev"
Requires-Dist: twine; extra == "dev"
